advsignals/__init__.py
DeepSignalLibrary-0.0.5.dist-info/LICENSE
DeepSignalLibrary-0.0.5.dist-info/METADATA
DeepSignalLibrary-0.0.5.dist-info/WHEEL
DeepSignalLibrary-0.0.5.dist-info/entry_points.txt
DeepSignalLibrary-0.0.5.dist-info/top_level.txt
DeepSignalLibrary-0.0.5.dist-info/RECORD
