Metadata-Version: 2.1
Name: DeepSignalLibrary
Version: 0.0.5
Summary: Adversarial Signal Library
Home-page: https://github.com/whatparty/advsignals
Author: yangzhaowei
Author-email: yangzw_@outlook.com
License: MIT
Keywords: Adversarial Signal Library
Classifier: Programming Language :: Python :: 3
Classifier: License :: OSI Approved :: MIT License
Classifier: Operating System :: OS Independent
License-File: LICENSE
Requires-Dist: torchvision (==0.11.1)
Requires-Dist: tqdm (==4.62.3)
